{
	"matchid": 1,
	"team1": {
		"name": "RECKLESS",
		"players": {
			"76561199060500915": "Fyle!",
			"76561198026701532": "ITAGUI ❟❛❟",
			"76561198986051330": "Barão",
			"76561198029293264": "Leucz",
			"76561198008963369": "unitw0w~"
		}
	},
	"team2": {
		"name": "NOSENSE",
		"players": {
			"76561198024690631": "ana0",
			"76561199109991417": "Aksman",
			"76561199777821301": "Finkz",
			"76561199523858737": "lk",
			"76561198997728848": "nardoX"
		}
	},
	"num_maps": 9,
	"maplist": [
		"de_mirage",
		"de_ancient",
		"de_dust2",
		"de_inferno",
		"de_nuke",
		"de_train",
		"de_anubis",
		"de_overpass",
		"de_vertigo"
	],
	"map_sides": [
		"knife",
		"knife",
		"knife",
		"knife",
		"knife",
		"knife",
		"knife",
		"knife",
		"knife"
	],
	"spectators": {
		"players": {
			"76561199478324598": "alieN"
		}
	},
	"clinch_series": false,
	"players_per_team": 5,
	"cvars": {
		"hostname": "RECKLESS vs. NONAME"
	}
}
